aceaccount/configuration.py
aceaccount/main.py
aceaccount/core/model_account_object.py
aceaccount/core/model_account_object_action_entities.py
aceaccount/core/model_account_object_instances.py
aceaccount/core/model_account_object_sql_entities.py
aceaccount/core/model_account_object_statement.py
aceaccount/services/account_objects_compare_service.py
aceaccount/services/account_objects_metadata_service.py
aceaccount/services/account_objects_solution_service.py
aceaccount/services/account_objects_validation_service.py
acedeploy/main.py
acedeploy/core/model_configuration.py
acedeploy/core/model_database_object.py
acedeploy/core/model_db_statement.py
acedeploy/core/model_git_entities.py
acedeploy/core/model_instance_objects.py
acedeploy/core/model_object_action_entities.py
acedeploy/core/model_prepostdeploymentsteps.py
acedeploy/core/model_solution_entities.py
acedeploy/core/model_sql_entities.py
acedeploy/extensions/comparer.py
acedeploy/extensions/export_dependency_graph.py
acedeploy/extensions/permissions.py
acedeploy/extensions/persist_views_table.py
acedeploy/extensions/plot_dependency_graph.py
acedeploy/extensions/smoketest.py
acedeploy/services/db_compare_service.py
acedeploy/services/dependency_parser.py
acedeploy/services/deploy_service.py
acedeploy/services/git_service.py
acedeploy/services/metadata_service.py
acedeploy/services/policy_service.py
acedeploy/services/secret_service.py
acedeploy/services/solution_service.py
aceservices/snowflake_service.py
aceutils/action_generator.py
aceutils/action_order_util.py
aceutils/database_management.py
aceutils/dict_and_list_util.py
aceutils/file_util.py
aceutils/general_util.py
aceutils/graphtools.py
aceutils/logger.py
aceutils/misc_utils.py
aceutils/parallelization_util.py
aceutils/string_util.py
docs/readme.md
resources/json-schemas/deployment.schema.json
resources/json-schemas/refresh-clone.schema.json
resources/json-schemas/smoketest.schema.json
acedeploy-2.4.295.dist-info/METADATA
acedeploy-2.4.295.dist-info/WHEEL
acedeploy-2.4.295.dist-info/top_level.txt
acedeploy-2.4.295.dist-info/RECORD
