Metadata-Version: 2.4
Name: acedeploy
Version: 2.4.295
Summary: Deployment framework for Snowflake DWH
Author-email: initions <ICSMC_EXT_PYPIORG@accenture.com>
License: MIT
Requires-Python: >=3.11
Requires-Dist: snowflake-connector-python==3.14.0
Requires-Dist: gitpython==3.1.42
Requires-Dist: jsonschema==4.23.0
Requires-Dist: networkx==3.2.1
Requires-Dist: regex==2024.9.11
